hi_dmario24/__init__.py
hi_dmario24/hello.py
hi_dmario24-0.8.0.dist-info/METADATA
hi_dmario24-0.8.0.dist-info/WHEEL
hi_dmario24-0.8.0.dist-info/entry_points.txt
hi_dmario24-0.8.0.dist-info/top_level.txt
hi_dmario24-0.8.0.dist-info/RECORD
