Metadata-Version: 2.1
Name: hi_dmario24
Version: 0.8.0
Summary: Default template for PDM package
Author-email: dMario24 <data.mario24@gmail.com>
License: MIT
Requires-Python: ==3.12.*
